{
    "name": "                            128 TERMINAL VIDA NOVA / TERMINAL OURO VERDE (INCLUSIVO)LINHA\r",
    "web_code": "1396",
    "polyline_ida": [
        {
            "lat": -22.974563,
            "lng": -47.171338
        },
        {
            "lat": -22.974735,
            "lng": -47.171423
        },
        {
            "lat": -22.975112,
            "lng": -47.171422
        },
        {
            "lat": -22.975153,
            "lng": -47.17134
        },
        {
            "lat": -22.975154,
            "lng": -47.171258
        },
        {
            "lat": -22.975138,
            "lng": -47.171164
        },
        {
            "lat": -22.974795,
            "lng": -47.171133
        },
        {
            "lat": -22.974667,
            "lng": -47.171107
        },
        {
            "lat": -22.974562,
            "lng": -47.171083
        },
        {
            "lat": -22.973719,
            "lng": -47.171087
        },
        {
            "lat": -22.973533,
            "lng": -47.171087
        },
        {
            "lat": -22.973516,
            "lng": -47.170389
        },
        {
            "lat": -22.973502,
            "lng": -47.170062
        },
        {
            "lat": -22.973467,
            "lng": -47.169767
        },
        {
            "lat": -22.973429,
            "lng": -47.169532
        },
        {
            "lat": -22.973366,
            "lng": -47.169128
        },
        {
            "lat": -22.973328,
            "lng": -47.168926
        },
        {
            "lat": -22.97317,
            "lng": -47.168352
        },
        {
            "lat": -22.97281,
            "lng": -47.1684
        },
        {
            "lat": -22.972459,
            "lng": -47.168496
        },
        {
            "lat": -22.972263,
            "lng": -47.168551
        },
        {
            "lat": -22.972099,
            "lng": -47.168618
        },
        {
            "lat": -22.971981,
            "lng": -47.168691
        },
        {
            "lat": -22.971594,
            "lng": -47.168976
        },
        {
            "lat": -22.971225,
            "lng": -47.169291
        },
        {
            "lat": -22.9711,
            "lng": -47.169384
        },
        {
            "lat": -22.970822,
            "lng": -47.168976
        },
        {
            "lat": -22.970046,
            "lng": -47.167852
        },
        {
            "lat": -22.969906,
            "lng": -47.167655
        },
        {
            "lat": -22.969777,
            "lng": -47.167482
        },
        {
            "lat": -22.969582,
            "lng": -47.167156
        },
        {
            "lat": -22.969393,
            "lng": -47.166804
        },
        {
            "lat": -22.969119,
            "lng": -47.166187
        },
        {
            "lat": -22.96907,
            "lng": -47.166048
        },
        {
            "lat": -22.968973,
            "lng": -47.165824
        },
        {
            "lat": -22.96913,
            "lng": -47.165746
        },
        {
            "lat": -22.969595,
            "lng": -47.16554
        },
        {
            "lat": -22.970161,
            "lng": -47.165264
        },
        {
            "lat": -22.969629,
            "lng": -47.163757
        },
        {
            "lat": -22.969067,
            "lng": -47.163954
        },
        {
            "lat": -22.968533,
            "lng": -47.164128
        },
        {
            "lat": -22.968386,
            "lng": -47.164178
        },
        {
            "lat": -22.968163,
            "lng": -47.16327
        },
        {
            "lat": -22.968096,
            "lng": -47.162966
        },
        {
            "lat": -22.967853,
            "lng": -47.161859
        },
        {
            "lat": -22.967645,
            "lng": -47.160813
        },
        {
            "lat": -22.967565,
            "lng": -47.160208
        },
        {
            "lat": -22.9675,
            "lng": -47.159547
        },
        {
            "lat": -22.967488,
            "lng": -47.158826
        },
        {
            "lat": -22.967527,
            "lng": -47.158265
        },
        {
            "lat": -22.96756,
            "lng": -47.157666
        },
        {
            "lat": -22.967582,
            "lng": -47.15724
        },
        {
            "lat": -22.967634,
            "lng": -47.155667
        },
        {
            "lat": -22.967816,
            "lng": -47.153381
        },
        {
            "lat": -22.967879,
            "lng": -47.153079
        },
        {
            "lat": -22.967953,
            "lng": -47.152764
        },
        {
            "lat": -22.967991,
            "lng": -47.152
        },
        {
            "lat": -22.968035,
            "lng": -47.151278
        },
        {
            "lat": -22.968069,
            "lng": -47.150575
        },
        {
            "lat": -22.968096,
            "lng": -47.150237
        },
        {
            "lat": -22.968118,
            "lng": -47.149855
        },
        {
            "lat": -22.968119,
            "lng": -47.149793
        },
        {
            "lat": -22.96814,
            "lng": -47.149358
        },
        {
            "lat": -22.968149,
            "lng": -47.14906
        },
        {
            "lat": -22.968167,
            "lng": -47.148828
        },
        {
            "lat": -22.968171,
            "lng": -47.148747
        },
        {
            "lat": -22.9682,
            "lng": -47.14809
        },
        {
            "lat": -22.968241,
            "lng": -47.147438
        },
        {
            "lat": -22.968249,
            "lng": -47.147112
        },
        {
            "lat": -22.968255,
            "lng": -47.146808
        },
        {
            "lat": -22.968251,
            "lng": -47.14654
        },
        {
            "lat": -22.968251,
            "lng": -47.146372
        },
        {
            "lat": -22.968229,
            "lng": -47.146125
        },
        {
            "lat": -22.968209,
            "lng": -47.145952
        },
        {
            "lat": -22.968189,
            "lng": -47.145759
        },
        {
            "lat": -22.968141,
            "lng": -47.145401
        },
        {
            "lat": -22.967959,
            "lng": -47.144682
        },
        {
            "lat": -22.967939,
            "lng": -47.144592
        },
        {
            "lat": -22.9679,
            "lng": -47.144358
        },
        {
            "lat": -22.967868,
            "lng": -47.144122
        },
        {
            "lat": -22.967789,
            "lng": -47.143581
        },
        {
            "lat": -22.967758,
            "lng": -47.143186
        },
        {
            "lat": -22.967742,
            "lng": -47.142856
        },
        {
            "lat": -22.967746,
            "lng": -47.14266
        },
        {
            "lat": -22.967756,
            "lng": -47.142465
        },
        {
            "lat": -22.967679,
            "lng": -47.141538
        },
        {
            "lat": -22.967379,
            "lng": -47.139573
        },
        {
            "lat": -22.967285,
            "lng": -47.138948
        },
        {
            "lat": -22.967175,
            "lng": -47.138292
        },
        {
            "lat": -22.967065,
            "lng": -47.137686
        },
        {
            "lat": -22.966786,
            "lng": -47.136053
        },
        {
            "lat": -22.966655,
            "lng": -47.135409
        },
        {
            "lat": -22.966611,
            "lng": -47.135321
        },
        {
            "lat": -22.966532,
            "lng": -47.135185
        },
        {
            "lat": -22.966437,
            "lng": -47.135043
        },
        {
            "lat": -22.966368,
            "lng": -47.134964
        },
        {
            "lat": -22.96631,
            "lng": -47.134909
        },
        {
            "lat": -22.96623,
            "lng": -47.134839
        },
        {
            "lat": -22.966018,
            "lng": -47.134691
        },
        {
            "lat": -22.965858,
            "lng": -47.134599
        },
        {
            "lat": -22.965645,
            "lng": -47.134456
        },
        {
            "lat": -22.965418,
            "lng": -47.134289
        },
        {
            "lat": -22.965003,
            "lng": -47.133989
        },
        {
            "lat": -22.96569,
            "lng": -47.13308
        },
        {
            "lat": -22.965633,
            "lng": -47.132956
        },
        {
            "lat": -22.965552,
            "lng": -47.132884
        },
        {
            "lat": -22.965201,
            "lng": -47.132572
        },
        {
            "lat": -22.964897,
            "lng": -47.132942
        },
        {
            "lat": -22.96483,
            "lng": -47.133031
        },
        {
            "lat": -22.964709,
            "lng": -47.1332
        },
        {
            "lat": -22.964639,
            "lng": -47.133278
        }
    ],
    "polyline_volta": [],
    "pontos": [
        {
            "lat": -22.965201,
            "lng": -47.132572
        },
        {
            "lat": -22.974563,
            "lng": -47.171338
        },
        {
            "lat": -22.973507,
            "lng": -47.169802
        },
        {
            "lat": -22.973329,
            "lng": -47.169782
        },
        {
            "lat": -22.972157,
            "lng": -47.168727
        },
        {
            "lat": -22.972032,
            "lng": -47.168577
        },
        {
            "lat": -22.969704,
            "lng": -47.164209
        },
        {
            "lat": -22.969822,
            "lng": -47.164161
        },
        {
            "lat": -22.968826,
            "lng": -47.164095
        },
        {
            "lat": -22.968738,
            "lng": -47.16402
        },
        {
            "lat": -22.967692,
            "lng": -47.161157
        },
        {
            "lat": -22.967854,
            "lng": -47.161021
        },
        {
            "lat": -22.967667,
            "lng": -47.156617
        },
        {
            "lat": -22.967502,
            "lng": -47.1566
        },
        {
            "lat": -22.968028,
            "lng": -47.152215
        },
        {
            "lat": -22.967836,
            "lng": -47.1517
        },
        {
            "lat": -22.967955,
            "lng": -47.149717
        },
        {
            "lat": -22.96818,
            "lng": -47.149503
        },
        {
            "lat": -22.968056,
            "lng": -47.147903
        },
        {
            "lat": -22.9683,
            "lng": -47.147804
        },
        {
            "lat": -22.968015,
            "lng": -47.145735
        },
        {
            "lat": -22.968247,
            "lng": -47.145714
        },
        {
            "lat": -22.967593,
            "lng": -47.143838
        },
        {
            "lat": -22.967849,
            "lng": -47.143379
        },
        {
            "lat": -22.967441,
            "lng": -47.141314
        },
        {
            "lat": -22.967586,
            "lng": -47.140704
        },
        {
            "lat": -22.967193,
            "lng": -47.1381
        },
        {
            "lat": -22.966788,
            "lng": -47.137455
        },
        {
            "lat": -22.9668,
            "lng": -47.135686
        },
        {
            "lat": -22.964717,
            "lng": -47.133174
        }
    ]
}